ocrgather-0.1.1.dist-info/METADATA
ocrgather-0.1.1.dist-info/WHEEL
ocrgather-0.1.1.dist-info/licenses/LICENSE
ocrgather/__init__.py
ocrgather-0.1.1.dist-info/RECORD
