Metadata-Version: 2.1
Name: OcrGather
Version: 0.1.1
Summary: Some third-party OCR services are encapsulated
Author-Email: centyuan <centyuan@outlook.com>
License: MIT
Requires-Python: >=3.8
Requires-Dist: twine>=4.0.2
Requires-Dist: alibabacloud-credentials>=0.3.2
